apolaai/__init__.py
apolaai/apolaai.py
apolaai-2.0.0.dist-info/licenses/LICENSE
apolaai-2.0.0.dist-info/METADATA
apolaai-2.0.0.dist-info/WHEEL
apolaai-2.0.0.dist-info/top_level.txt
apolaai-2.0.0.dist-info/RECORD
