Metadata-Version: 2.4
Name: apolaai
Version: 2.0.0
Summary: Python API client for ApolaAI server with Gemini 2.5 Flash + 50+ textbooks
Home-page: https://github.com/apolaai/apolaai-python
Author: ApolaAI
Author-email: support@apolaai.com
Project-URL: Bug Reports, https://github.com/apolaai/apolaai-python/issues
Project-URL: Source, https://github.com/apolaai/apolaai-python
Project-URL: Documentation, https://apolaai.com/docs
Project-URL: Website, https://apolaai.com
Keywords: ai,artificial intelligence,text generation,audio generation,image generation,gemini,elevenlabs,education,textbooks,sri lanka,apolaai,machine learning,nlp
Classifier: Development Status :: 4 - Beta
Classifier: Intended Audience :: Developers
Classifier: Intended Audience :: Education
Classifier: Topic :: Software Development :: Libraries :: Python Modules
Classifier: Topic :: Scientific/Engineering :: Artificial Intelligence
Classifier: Topic :: Education
Classifier: License :: OSI Approved :: MIT License
Classifier: Programming Language :: Python :: 3
Classifier: Programming Language :: Python :: 3.7
Classifier: Programming Language :: Python :: 3.8
Classifier: Programming Language :: Python :: 3.9
Classifier: Programming Language :: Python :: 3.10
Classifier: Programming Language :: Python :: 3.11
Classifier: Programming Language :: Python :: 3.12
Requires-Python: >=3.7
License-File: LICENSE
Requires-Dist: requests>=2.25.0
Requires-Dist: python-dotenv>=0.19.0
Dynamic: author
Dynamic: author-email
Dynamic: classifier
Dynamic: description
Dynamic: description-content-type
Dynamic: home-page
Dynamic: keywords
Dynamic: license-file
Dynamic: project-url
Dynamic: requires-dist
Dynamic: requires-python
Dynamic: summary
